sa_pathfinding/.DS_Store
sa_pathfinding/__init__.py
sa_pathfinding/__main__.py
sa_pathfinding/cli.py
sa_pathfinding/gui.py
sa_pathfinding/algorithms/__init__.py
sa_pathfinding/algorithms/astar/__init__.py
sa_pathfinding/algorithms/astar/generic_astar.py
sa_pathfinding/algorithms/astar/grid_optimized_astar.py
sa_pathfinding/algorithms/bfs/__init__.py
sa_pathfinding/algorithms/bfs/generic_bfs.py
sa_pathfinding/algorithms/dfs/__init__.py
sa_pathfinding/algorithms/dfs/generic_dfs.py
sa_pathfinding/algorithms/dijkstra/__init__.py
sa_pathfinding/algorithms/dijkstra/generic_dijkstra.py
sa_pathfinding/algorithms/dijkstra/grid_optimized_dijkstra.py
sa_pathfinding/algorithms/generics/__init__.py
sa_pathfinding/algorithms/generics/search.py
sa_pathfinding/algorithms/generics/search_node.py
sa_pathfinding/environments/__init__.py
sa_pathfinding/environments/generics/__init__.py
sa_pathfinding/environments/generics/env.py
sa_pathfinding/environments/generics/state.py
sa_pathfinding/environments/grids/__init__.py
sa_pathfinding/environments/grids/cardinal_grid.py
sa_pathfinding/environments/grids/octile_grid.py
sa_pathfinding/environments/grids/generics/__init__.py
sa_pathfinding/environments/grids/generics/grid.py
sa_pathfinding/environments/towers_of_hanoi/towers_of_hanoi.py
sa_pathfinding/heuristics/__init__.py
sa_pathfinding/heuristics/grid_heuristic.py
sa_pathfinding/heuristics/heuristic.py
sa_pathfinding-0.1.dist-info/AUTHORS.rst
sa_pathfinding-0.1.dist-info/LICENSE
sa_pathfinding-0.1.dist-info/METADATA
sa_pathfinding-0.1.dist-info/WHEEL
sa_pathfinding-0.1.dist-info/entry_points.txt
sa_pathfinding-0.1.dist-info/top_level.txt
sa_pathfinding-0.1.dist-info/RECORD
