Metadata-Version: 2.1
Name: sa-pathfinding
Version: 0.1
Summary: A Python utility to execute single-agent search algorithms and represent search environments.
Home-page: https://github.com/nathansamsel/python-sa-pathfinding
Author: Nathan Samsel
Author-email: nathan.d.samsel@gmail.com
License: MIT
Project-URL: Documentation, https://python-sa-pathfinding.readthedocs.io/
Project-URL: Changelog, https://python-sa-pathfinding.readthedocs.io/en/latest/changelog.html
Project-URL: Issue Tracker, https://github.com/nathansamsel/python-sa-pathfinding/issues
Keywords: search,single-agent search,pathfindingsa-pathfinding,python-sa-pathfinding,pathfinder,grid search
Platform: UNKNOWN
Classifier: Development Status :: 3 - Alpha
Classifier: Intended Audience :: Developers
Classifier: License :: OSI Approved :: MIT License
Classifier: Operating System :: Unix
Classifier: Operating System :: POSIX
Classifier: Operating System :: Microsoft :: Windows
Classifier: Programming Language :: Python
Classifier: Programming Language :: Python :: 3.7
Classifier: Programming Language :: Python :: 3.8
Classifier: Topic :: Utilities
Requires-Python: >=3.7
